Metadata-Version: 2.1
Name: newgistics
Version: 0.2
Summary: A python client library for Newgistics Web API and Fulfillments API
Home-page: https://github.com/sameerkumar18/newgistics
Author: Sameer Kumar
Author-email: sam@sameerkumar.website
License: Apache 2.0
Keywords: api wrapper client library newgistics rest web api fulfillments pitneybowes
Platform: UNKNOWN
Classifier: Development Status :: 4 - Beta
Classifier: Intended Audience :: Developers
Classifier: Operating System :: OS Independent
Classifier: License :: OSI Approved :: Apache Software License
Classifier: Programming Language :: Python
Classifier: Programming Language :: Python :: 3
Classifier: Programming Language :: Python :: 3.5
Classifier: Programming Language :: Python :: 3.6
Classifier: Programming Language :: Python :: 3.7
Classifier: Programming Language :: Python :: Implementation :: CPython
Classifier: Programming Language :: Python :: Implementation :: PyPy
Classifier: Topic :: Software Development
Classifier: Topic :: Software Development :: Libraries
Classifier: Topic :: Software Development :: Libraries :: Python Modules
Provides-Extra: dev
Provides-Extra: test
